{
    "status": "0",
    "error": "",
    "data": {
        "title": {
            "text": "我是词云图",
            "subtext": "我是词云图副标题",
            "source": "基数: 所有被访者 n=400 \n\n数据来源：B12"
        },
        "data": {
            "series": {
                "经典有机经典": 257305,
                "漂亮": 114720,
                "外观": 102398,
                "内饰": 83423,
                "真皮皮皮皮皮皮皮皮皮": 72421,
                "车型": 66957,
                "独特": 54156,
                "变速箱": 51562,
                "豪华": 50807,
                "大气": 49365,
                "设计": 49256,
                "座椅": 48472,
                "方向盘": 46811,
                "很潮": 44714,
                "时尚": 44414,
                "MT": 40839,
                "朴素": 38127,
                "简朴": 37931,
                "异响": 36265,
                "中控": 35160,
                "不好看": 27560,
                "颜色": 27041,
                "外形": 26931,
                "年轻": 25889,
                "运动": 24645,
                "做工": 24080,
                "前脸": 23649,
                "启动": 23181,
                "排量": 23147,
                "装饰板": 21857,
                "仪表": 20384,
                "隔音": 20154,
                "样子": 19656,
                "加油": 18292,
                "纯黑内饰": 18279,
                "噪音": 18139,
                "车门": 18084,
                "脚垫": 17546,
                "包裹": 16716,
                "整体": 16497,
                "手动挡": 15460,
                "硬塑": 15231,
                "转向": 15178,
                "后视镜": 14898,
                "涡轮": 14724,
                "高大上": 14429,
                "样子数鸭子": 19656,
                "加油数鸭子": 18292,
                "纯黑内饰数鸭子": 18279,
                "噪音数鸭子": 18139
            }
        }
    }
}
